goodbye_quota/__init__.py
goodbye_quota/client.py
goodbye_quota/key_manager.py
goodbye_quota-0.1.0.dist-info/licenses/LICENSE
goodbye_quota-0.1.0.dist-info/METADATA
goodbye_quota-0.1.0.dist-info/WHEEL
goodbye_quota-0.1.0.dist-info/top_level.txt
goodbye_quota-0.1.0.dist-info/RECORD
