Metadata-Version: 2.4
Name: goodbye_quota
Version: 0.1.0
Summary: A wrapper for Gemini API to handle multiple API keys and rotate them on quota exhaustion.
Home-page: https://github.com/cmpdchtr/GoodbyeQuota
Author: @cmpdchtr
Author-email: cmpdchtr@example.com
Classifier: Programming Language :: Python :: 3
Classifier: License :: OSI Approved :: MIT License
Classifier: Operating System :: OS Independent
Requires-Python: >=3.9
License-File: LICENSE
Requires-Dist: google-generativeai
Dynamic: author
Dynamic: author-email
Dynamic: classifier
Dynamic: description
Dynamic: description-content-type
Dynamic: home-page
Dynamic: license-file
Dynamic: requires-dist
Dynamic: requires-python
Dynamic: summary
